modules/__init__.py
modules/__init__.pyc
modules/colour.py
modules/colour.pyc
modules/common_functions.py
modules/common_functions.pyc
modules/common_help.py
modules/common_help.pyc
modules/deploy.py
modules/deploy.pyc
modules/execute_recipes.py
modules/execute_recipes.pyc
modules/setup.py
modules/setup.pyc
modules/update_custom_cookbooks.py
modules/update_custom_cookbooks.pyc
opsworks_cli-0.4.9.data/scripts/opsworks-cli
opsworks_cli-0.4.9.dist-info/DESCRIPTION.rst
opsworks_cli-0.4.9.dist-info/METADATA
opsworks_cli-0.4.9.dist-info/RECORD
opsworks_cli-0.4.9.dist-info/WHEEL
opsworks_cli-0.4.9.dist-info/metadata.json
opsworks_cli-0.4.9.dist-info/top_level.txt
