Metadata-Version: 2.0
Name: opsworks-cli
Version: 0.4.9
Summary: A simple python module to work with aws opsworks
Home-page: https://github.com/chaturanga50/opsworks-cli
Author: Chathuranga Abeyrathna
Author-email: chaturanga50@gmail.com
License: UNKNOWN
Project-URL: Source, https://github.com/chaturanga50/opsworks-cli
Project-URL: Bug Reports, https://github.com/chaturanga50/opsworks-cli/issues
Platform: UNKNOWN
Classifier: Development Status :: 5 - Production/Stable
Classifier: Intended Audience :: Developers
Classifier: Topic :: Software Development :: Build Tools
Classifier: License :: OSI Approved :: MIT License
Classifier: Programming Language :: Python :: 2.7
Requires-Dist: boto3
Requires-Dist: PTable
